ami2rabbitmq/__init__.py
ami2rabbitmq/ami_rabbitmq.py
ami2rabbitmq/entities.py
ami2rabbitmq/exceptions.py
ami2rabbitmq/logs_app.py
ami2rabbitmq/manager.py
ami2rabbitmq/rabbitmq.py
ami2rabbitmq/redis_db.py
ami2rabbitmq/repositories.py
ami2rabbitmq/utils.py
ami2rabbitmq-0.2.1.dist-info/LICENSE
ami2rabbitmq-0.2.1.dist-info/METADATA
ami2rabbitmq-0.2.1.dist-info/WHEEL
ami2rabbitmq-0.2.1.dist-info/top_level.txt
ami2rabbitmq-0.2.1.dist-info/RECORD
